LICENSE
MANIFEST.in
README.rst
pyproject.toml
requirements.txt
setup.cfg
setup.py
djedefre.egg-info/PKG-INFO
djedefre.egg-info/SOURCES.txt
djedefre.egg-info/dependency_links.txt
djedefre.egg-info/requires.txt
djedefre.egg-info/top_level.txt
djoser/__init__.py
djoser/compat.py
djoser/conf.py
djoser/constants.py
djoser/email.py
djoser/permissions.py
djoser/serializers.py
djoser/signals.py
djoser/utils.py
djoser/views.py
djoser/social/__init__.py
djoser/social/serializers.py
djoser/social/urls.py
djoser/social/views.py
djoser/social/backends/__init__.py
djoser/social/backends/facebook.py
djoser/social/token/__init__.py
djoser/social/token/jwt.py
djoser/templates/email/activation.html
djoser/templates/email/confirmation.html
djoser/templates/email/password_changed_confirmation.html
djoser/templates/email/password_reset.html
djoser/templates/email/username_changed_confirmation.html
djoser/templates/email/username_reset.html
djoser/urls/__init__.py
djoser/urls/authtoken.py
djoser/urls/base.py
djoser/urls/jwt.py